_models_hcs_mgw/__init__.py
_models_hcs_mgw/models/__init__.py
_models_hcs_mgw/models/_address_detail.py
_models_hcs_mgw/models/_audit.py
_models_hcs_mgw/models/_create_address_info.py
_models_hcs_mgw/models/_create_address_request.py
_models_hcs_mgw/models/_create_address_response.py
_models_hcs_mgw/models/_create_agent_info.py
_models_hcs_mgw/models/_create_agent_request.py
_models_hcs_mgw/models/_create_agent_response.py
_models_hcs_mgw/models/_create_job_info.py
_models_hcs_mgw/models/_create_job_request.py
_models_hcs_mgw/models/_create_job_response.py
_models_hcs_mgw/models/_create_report_info.py
_models_hcs_mgw/models/_create_report_request.py
_models_hcs_mgw/models/_create_report_response.py
_models_hcs_mgw/models/_create_tunnel_info.py
_models_hcs_mgw/models/_create_tunnel_request.py
_models_hcs_mgw/models/_create_tunnel_response.py
_models_hcs_mgw/models/_delete_address_response.py
_models_hcs_mgw/models/_delete_agent_response.py
_models_hcs_mgw/models/_delete_job_request.py
_models_hcs_mgw/models/_delete_job_response.py
_models_hcs_mgw/models/_delete_tunnel_response.py
_models_hcs_mgw/models/_file_type_filters.py
_models_hcs_mgw/models/_filter_rule.py
_models_hcs_mgw/models/_get_address_resp.py
_models_hcs_mgw/models/_get_address_response.py
_models_hcs_mgw/models/_get_address_response_body.py
_models_hcs_mgw/models/_get_agent_resp.py
_models_hcs_mgw/models/_get_agent_response.py
_models_hcs_mgw/models/_get_agent_response_body.py
_models_hcs_mgw/models/_get_agent_status_resp.py
_models_hcs_mgw/models/_get_agent_status_response.py
_models_hcs_mgw/models/_get_agent_status_response_body.py
_models_hcs_mgw/models/_get_job_request.py
_models_hcs_mgw/models/_get_job_resp.py
_models_hcs_mgw/models/_get_job_response.py
_models_hcs_mgw/models/_get_job_response_body.py
_models_hcs_mgw/models/_get_job_result_request.py
_models_hcs_mgw/models/_get_job_result_resp.py
_models_hcs_mgw/models/_get_job_result_response.py
alibabacloud_gateway_oss_util-0.0.9.dist-info/METADATA
alibabacloud_gateway_oss_util-0.0.9.dist-info/WHEEL
alibabacloud_gateway_oss_util-0.0.9.dist-info/top_level.txt
alibabacloud_gateway_oss_util-0.0.9.dist-info/RECORD
